app/build_test.py
study_ai-0.0.1.dist-info/LICENSE
study_ai-0.0.1.dist-info/METADATA
study_ai-0.0.1.dist-info/WHEEL
study_ai-0.0.1.dist-info/top_level.txt
study_ai-0.0.1.dist-info/RECORD
