Metadata-Version: 2.1
Name: study-ai
Version: 0.0.1
Summary: The library was developed to help students study AI.
Home-page: https://lingua.blog.me/221789288704
Author: EunJae Yong (Jay Yong)
Author-email: jayyong.dev@gmail.com
License: MIT
Platform: UNKNOWN
Requires-Python: >=3.6
License-File: LICENSE
